slogger/__init__.py
super_logger-1.0.dist-info/METADATA
super_logger-1.0.dist-info/WHEEL
super_logger-1.0.dist-info/top_level.txt
super_logger-1.0.dist-info/RECORD
