Metadata-Version: 2.1
Name: super-logger
Version: 1.0
Summary: super-logger!
Author: wer310Libs
Author-email: oficalkapudovo@gmail.com
Classifier: Programming Language :: Python :: 3
